{
  "articles": [
    { "id": "art-001", "title": "Carrot Varieties for High-Volume Kitchens", "category": "Roots", "slug": "carrot-varieties-high-volume-kitchens" },
    { "id": "art-002", "title": "Yellow Onion Buying Notes for Foodservice", "category": "Alliums", "slug": "yellow-onion-foodservice-buying-notes" },
    { "id": "art-003", "title": "Red Onion Storage and Yield Planning", "category": "Alliums", "slug": "red-onion-storage-yield-planning" },
    { "id": "art-004", "title": "Shallots vs. Cipollini for Restaurant Menus", "category": "Alliums", "slug": "shallots-vs-cipollini-restaurant-menus" },
    { "id": "art-005", "title": "Leeks in Winter Menu Development", "category": "Alliums", "slug": "leeks-winter-menu-development" },
    { "id": "art-006", "title": "Baby Chioggia Beets and Color Retention", "category": "Roots", "slug": "baby-chioggia-beets-color-retention" },
    { "id": "art-007", "title": "Golden Beets for Prepared Foods Programs", "category": "Roots", "slug": "golden-beets-prepared-foods" },
    { "id": "art-008", "title": "Parsnip Seasonality and Trim Loss", "category": "Roots", "slug": "parsnip-seasonality-trim-loss" },
    { "id": "art-009", "title": "Turnips, Rutabagas, and Cold-Weather Demand", "category": "Roots", "slug": "turnips-rutabagas-cold-weather-demand" },
    { "id": "art-010", "title": "Daikon Radish Uses Beyond Garnish", "category": "Roots", "slug": "daikon-radish-beyond-garnish" },
    { "id": "art-011", "title": "Fingerling Potatoes for Banquet Service", "category": "Tubers", "slug": "fingerling-potatoes-banquet-service" },
    { "id": "art-012", "title": "Yukon Gold Potato Size Profiles", "category": "Tubers", "slug": "yukon-gold-potato-size-profiles" },
    { "id": "art-013", "title": "Sweet Potatoes Across Fall Menus", "category": "Tubers", "slug": "sweet-potatoes-fall-menus" },
    { "id": "art-014", "title": "Sunchokes and Specialty Root Demand", "category": "Tubers", "slug": "sunchokes-specialty-root-demand" },
    { "id": "art-015", "title": "Broccolini vs. Baby Broccoli", "category": "Brassicas", "slug": "broccolini-vs-baby-broccoli" },
    { "id": "art-016", "title": "Cauliflower Color Mixes for Catering", "category": "Brassicas", "slug": "cauliflower-color-mixes-catering" },
    { "id": "art-017", "title": "Romanesco Quality Checks", "category": "Brassicas", "slug": "romanesco-quality-checks" },
    { "id": "art-018", "title": "Brussels Sprouts Stalks vs. Bulk Packs", "category": "Brassicas", "slug": "brussels-sprouts-stalks-bulk-packs" },
    { "id": "art-019", "title": "Lacinato Kale for Prep Teams", "category": "Greens", "slug": "lacinato-kale-prep-teams" },
    { "id": "art-020", "title": "Swiss Chard Color and Shelf Life", "category": "Greens", "slug": "swiss-chard-color-shelf-life" },
    { "id": "art-021", "title": "Arugula Heat and Peppery Flavor", "category": "Greens", "slug": "arugula-heat-peppery-flavor" },
    { "id": "art-022", "title": "Baby Spinach Handling for Salad Bars", "category": "Greens", "slug": "baby-spinach-salad-bar-handling" },
    { "id": "art-023", "title": "Romaine Hearts for Fast Casual Programs", "category": "Greens", "slug": "romaine-hearts-fast-casual" },
    { "id": "art-024", "title": "Basil, Mint, and Tender Herb Rotation", "category": "Herbs", "slug": "basil-mint-tender-herb-rotation" },
    { "id": "art-025", "title": "Cilantro Bunch Quality and Shrink", "category": "Herbs", "slug": "cilantro-bunch-quality-shrink" },
    { "id": "art-026", "title": "Parsley Flat Leaf vs. Curly", "category": "Herbs", "slug": "parsley-flat-leaf-vs-curly" },
    { "id": "art-027", "title": "Thyme and Rosemary for Roasting Menus", "category": "Herbs", "slug": "thyme-rosemary-roasting-menus" },
    { "id": "art-028", "title": "Cremini Mushroom Yield Planning", "category": "Mushrooms", "slug": "cremini-mushroom-yield-planning" },
    { "id": "art-029", "title": "Shiitake Caps for Umami-Forward Dishes", "category": "Mushrooms", "slug": "shiitake-caps-umami-dishes" },
    { "id": "art-030", "title": "Oyster Mushroom Cluster Handling", "category": "Mushrooms", "slug": "oyster-mushroom-cluster-handling" },
    { "id": "art-031", "title": "Maitake and Specialty Mushroom Demand", "category": "Mushrooms", "slug": "maitake-specialty-mushroom-demand" },
    { "id": "art-032", "title": "Heirloom Tomatoes and Summer Pricing", "category": "Fruiting Vegetables", "slug": "heirloom-tomatoes-summer-pricing" },
    { "id": "art-033", "title": "Cherry Tomato Pack Styles", "category": "Fruiting Vegetables", "slug": "cherry-tomato-pack-styles" },
    { "id": "art-034", "title": "Bell Pepper Color Mix Forecasting", "category": "Fruiting Vegetables", "slug": "bell-pepper-color-mix-forecasting" },
    { "id": "art-035", "title": "Japanese Eggplant for Grill Menus", "category": "Fruiting Vegetables", "slug": "japanese-eggplant-grill-menus" },
    { "id": "art-036", "title": "Zucchini and Squash Blossom Planning", "category": "Squash", "slug": "zucchini-squash-blossom-planning" },
    { "id": "art-037", "title": "Butternut Squash Yield and Labor", "category": "Squash", "slug": "butternut-squash-yield-labor" },
    { "id": "art-038", "title": "Specialty Citrus for Beverage Programs", "category": "Fruit", "slug": "specialty-citrus-beverage-programs" },
    { "id": "art-039", "title": "Stone Fruit Ripeness for Restaurants", "category": "Fruit", "slug": "stone-fruit-ripeness-restaurants" },
    { "id": "art-040", "title": "Persimmons and Late-Fall Menu Timing", "category": "Fruit", "slug": "persimmons-late-fall-menu-timing" }
  ],
  "engagement": []
}
